mindfoundry.client.horizon-2.13.12-py3.8-nspkg.pth
mindfoundry/client/horizon/__init__.py
mindfoundry/client/horizon/client/__init__.py
mindfoundry/client/horizon/client/datasets_client.py
mindfoundry/client/horizon/client/horizon_client.py
mindfoundry/client/horizon/client/pipelines_client.py
mindfoundry/client/horizon/client/utils.py
mindfoundry/client/horizon/generated/__init__.py
mindfoundry/client/horizon/generated/client.py
mindfoundry/client/horizon/generated/types.py
mindfoundry/client/horizon/generated/api/__init__.py
mindfoundry/client/horizon/generated/api/algos/__init__.py
mindfoundry/client/horizon/generated/api/algos/delete_algo_resource.py
mindfoundry/client/horizon/generated/api/algos/get_algo_resource.py
mindfoundry/client/horizon/generated/api/algos/get_algo_symbols_resource.py
mindfoundry/client/horizon/generated/api/algos/get_algo_test_cases_resource.py
mindfoundry/client/horizon/generated/api/algos/get_all_algo_resource.py
mindfoundry/client/horizon/generated/api/algos/post_algo_cloning_resource.py
mindfoundry/client/horizon/generated/api/algos/post_algo_test_resource.py
mindfoundry/client/horizon/generated/api/algos/post_all_algo_resource.py
mindfoundry/client/horizon/generated/api/algos/put_algo_resource.py
mindfoundry/client/horizon/generated/api/api_keys/__init__.py
mindfoundry/client/horizon/generated/api/api_keys/post_api_key_resource.py
mindfoundry/client/horizon/generated/api/datasets/__init__.py
mindfoundry/client/horizon/generated/api/datasets/delete_individual_dataset_resource.py
mindfoundry/client/horizon/generated/api/datasets/get_column_acf_resource.py
mindfoundry/client/horizon/generated/api/datasets/get_column_correlation_resource.py
mindfoundry/client/horizon/generated/api/datasets/get_column_mi_resource.py
mindfoundry/client/horizon/generated/api/datasets/get_column_plot_resource.py
mindfoundry/client/horizon/generated/api/datasets/get_data_slice_resource.py
mindfoundry.client.horizon-2.13.12.dist-info/LICENSE
mindfoundry.client.horizon-2.13.12.dist-info/METADATA
mindfoundry.client.horizon-2.13.12.dist-info/WHEEL
mindfoundry.client.horizon-2.13.12.dist-info/namespace_packages.txt
mindfoundry.client.horizon-2.13.12.dist-info/top_level.txt
mindfoundry.client.horizon-2.13.12.dist-info/RECORD
