Metadata-Version: 2.1
Name: mindfoundry.client.horizon
Version: 2.13.12
Summary: Mind Foundry Horizon Client
Home-page: https://mindfoundry.ai/horizon
Author: Mind Foundry Ltd
Author-email: support@mindfoundry.ai
License: MIT
Platform: UNKNOWN
Classifier: Development Status :: 3 - Alpha
Classifier: Programming Language :: Python :: 3
Classifier: Intended Audience :: Developers
Classifier: Intended Audience :: Financial and Insurance Industry
Classifier: Intended Audience :: Science/Research
Classifier: Topic :: Scientific/Engineering :: Artificial Intelligence
Classifier: License :: OSI Approved :: MIT License
Classifier: Operating System :: OS Independent
Requires-Dist: numpy (>=1.17.3)
Requires-Dist: pandas (>=1.3.5)
Requires-Dist: requests
Requires-Dist: attrs
Requires-Dist: httpx (<0.19,>=0.16.1)
Requires-Dist: python-dateutil
Provides-Extra: all
Requires-Dist: numpy (>=1.17.3) ; extra == 'all'
Requires-Dist: pandas (>=1.3.5) ; extra == 'all'
Requires-Dist: requests ; extra == 'all'
Requires-Dist: attrs ; extra == 'all'
Requires-Dist: httpx (<0.19,>=0.16.1) ; extra == 'all'
Requires-Dist: python-dateutil ; extra == 'all'
Requires-Dist: black (==20.8b1) ; extra == 'all'
Requires-Dist: click (==7.1.2) ; extra == 'all'
Requires-Dist: check-manifest (==0.46) ; extra == 'all'
Requires-Dist: coverage (==5.5) ; extra == 'all'
Requires-Dist: isort (==5.8.0) ; extra == 'all'
Requires-Dist: mypy (==0.812) ; extra == 'all'
Requires-Dist: openapi-python-client (==0.10.0) ; extra == 'all'
Requires-Dist: pip-tools (==6.1.0) ; extra == 'all'
Requires-Dist: pre-commit (==2.11.1) ; extra == 'all'
Requires-Dist: pylint (==2.7.2) ; extra == 'all'
Requires-Dist: pytest (==6.2.4) ; extra == 'all'
Requires-Dist: pytest-httpx (==0.12.0) ; extra == 'all'
Requires-Dist: pytest-timeout (==1.4.2) ; extra == 'all'
Requires-Dist: pytest-tldr (==0.2.4) ; extra == 'all'
Requires-Dist: pytest-asyncio (==0.14.0) ; extra == 'all'
Requires-Dist: bandit (==1.7.0) ; extra == 'all'
Requires-Dist: matplotlib (==3.5.2) ; extra == 'all'
Provides-Extra: dev
Requires-Dist: black (==20.8b1) ; extra == 'dev'
Requires-Dist: click (==7.1.2) ; extra == 'dev'
Requires-Dist: check-manifest (==0.46) ; extra == 'dev'
Requires-Dist: coverage (==5.5) ; extra == 'dev'
Requires-Dist: isort (==5.8.0) ; extra == 'dev'
Requires-Dist: mypy (==0.812) ; extra == 'dev'
Requires-Dist: openapi-python-client (==0.10.0) ; extra == 'dev'
Requires-Dist: pip-tools (==6.1.0) ; extra == 'dev'
Requires-Dist: pre-commit (==2.11.1) ; extra == 'dev'
Requires-Dist: pylint (==2.7.2) ; extra == 'dev'
Requires-Dist: pytest (==6.2.4) ; extra == 'dev'
Requires-Dist: pytest-httpx (==0.12.0) ; extra == 'dev'
Requires-Dist: pytest-timeout (==1.4.2) ; extra == 'dev'
Requires-Dist: pytest-tldr (==0.2.4) ; extra == 'dev'
Requires-Dist: pytest-asyncio (==0.14.0) ; extra == 'dev'
Requires-Dist: bandit (==1.7.0) ; extra == 'dev'
Requires-Dist: matplotlib (==3.5.2) ; extra == 'dev'
